odoo/addons/knowledge_translatable_pages/CHANGELOG.md
odoo/addons/knowledge_translatable_pages/README.rst
odoo/addons/knowledge_translatable_pages/__init__.py
odoo/addons/knowledge_translatable_pages/__manifest__.py
odoo/addons/knowledge_translatable_pages/models/__init__.py
odoo/addons/knowledge_translatable_pages/models/document_page.py
odoo/addons/knowledge_translatable_pages/static/description/icon.png
odoo/addons/knowledge_translatable_pages/views/document_page_view.xml
odoo12_addon_knowledge_translatable_pages-12.0.1.0.0.dist-info/METADATA
odoo12_addon_knowledge_translatable_pages-12.0.1.0.0.dist-info/WHEEL
odoo12_addon_knowledge_translatable_pages-12.0.1.0.0.dist-info/top_level.txt
odoo12_addon_knowledge_translatable_pages-12.0.1.0.0.dist-info/RECORD
