Metadata-Version: 2.1
Name: odoo12-addon-knowledge-translatable-pages
Version: 12.0.1.0.0
Summary: Translated Knowledge Pages and Categories
Home-page: https://gitlab.com/somitcoop/erp-research/odoo-helpdesk
Author: Som It Cooperatiu SCCL, Som Connexió SCCL, Odoo Community Association (OCA)
Author-email: support@odoo-community.org
License: AGPL-3
Platform: UNKNOWN
Classifier: Programming Language :: Python
Classifier: Framework :: Odoo
Classifier: Framework :: Odoo :: 12.0
Classifier: License :: OSI Approved :: GNU Affero General Public License v3
Requires-Python: >=3.5
Requires-Dist: odoo12-addon-document-page
Requires-Dist: odoo12-addon-knowledge
Requires-Dist: odoo <12.1dev,>=12.0a
